odoo/addons/storage_backend_sftp/README.rst
odoo/addons/storage_backend_sftp/__init__.py
odoo/addons/storage_backend_sftp/__manifest__.py
odoo/addons/storage_backend_sftp/components/__init__.py
odoo/addons/storage_backend_sftp/components/sftp_adapter.py
odoo/addons/storage_backend_sftp/i18n/it.po
odoo/addons/storage_backend_sftp/i18n/storage_backend_sftp.pot
odoo/addons/storage_backend_sftp/models/__init__.py
odoo/addons/storage_backend_sftp/models/storage_backend.py
odoo/addons/storage_backend_sftp/static/description/icon.png
odoo/addons/storage_backend_sftp/tests/__init__.py
odoo/addons/storage_backend_sftp/tests/test_sftp.py
odoo/addons/storage_backend_sftp/views/backend_storage_view.xml
odoo_addon_storage_backend_sftp-18.0.1.0.0.4.dist-info/METADATA
odoo_addon_storage_backend_sftp-18.0.1.0.0.4.dist-info/WHEEL
odoo_addon_storage_backend_sftp-18.0.1.0.0.4.dist-info/top_level.txt
odoo_addon_storage_backend_sftp-18.0.1.0.0.4.dist-info/RECORD
